[],
"campusCode": "NB",
"index": "09662",
"unitMajors": [],
"printed": "N",
"specialPermissionAddCodeDescription": null,
"subtitle": null,
"meetingTimes": [
    {
        "campusLocation": "2",
        "baClassHours": null,
        "roomNumber": "103",
        "pmCode": "P",
        "campusAbbrev": "BUS",
        "campusName": "BUSCH",
        "meetingDay": "T",
        "buildingCode": "ARC",
        "startTime": "0200",
        "endTime": "0320",
        "meetingModeDesc": "LEC",
        "meetingModeCode": "02"
    },
    {
        "campusLocation": "3",
        "baClassHours": null,
        "roomNumber": "B123",
        "pmCode": "A",
        "campusAbbrev": "LIV",
        "campusName": "LIVINGSTON",
        "meetingDay": "W",
        "buildingCode": "LSH",
        "startTime": "1035",
        "endTime": "1130",
        "meetingModeDesc": "RECIT",
        "meetingModeCode": "03"
    },
    {
        "campusLocation": "2",
        "baClassHours": null,
        "roomNumber": "103",
        "pmCode": "P",
        "campusAbbrev": "BUS",
        "campusName": "BUSCH",
        "meetingDay": "TH",
        "buildingCode": "ARC",
        "startTime": "0200",
        "endTime": "0320",
        "meetingModeDesc": "LEC",
        "meetingModeCode": "02"
    }
],
"legendKey": null,
"honorPrograms": []
},
{
"sectionEligibility": null,
"sessionDatePrintIndicator": "N",
"examCode": "M",
"specialPermissionAddCode": null,
"crossListedSections": [],
"sectionNotes": null,
"specialPermissionDropCode": null,
"instructors": [],
"number": "25",
"majors": [],
"sessionDates": null,
"specialPermissionDropCodeDescription": null,
"subtopic": null,
"openStatus": true,
"comments": [
    {
        "code": "05",
        "description": "Go to http://canvas.rutgers.edu"
    }
],"min